OVM_diver/OVM_diver.py
OVM_diver/__init__.py
ovm_diver-0.0.2.dist-info/METADATA
ovm_diver-0.0.2.dist-info/WHEEL
ovm_diver-0.0.2.dist-info/licenses/LICENSE.txt
ovm_diver-0.0.2.dist-info/RECORD
