Metadata-Version: 2.1
Name: OVM_diver
Version: 0.0.2
Summary: OVM_diver provides some basic mixed gas calculations
Project-URL: Homepage, https://github.com/data-project/ovm-diver
Author-email: data-project <ferry@fobic.nl>
License-File: LICENSE.txt
Classifier: License :: OSI Approved :: MIT License
Classifier: Operating System :: OS Independent
Classifier: Programming Language :: Python :: 3
Requires-Python: >=3.7
